fastapi_rest_jsonapi/__init__.py
fastapi_rest_jsonapi/rest_api.py
fastapi_rest_jsonapi/common/__init__.py
fastapi_rest_jsonapi/common/enum.py
fastapi_rest_jsonapi/common/exceptions.py
fastapi_rest_jsonapi/common/memoized_property.py
fastapi_rest_jsonapi/common/methods.py
fastapi_rest_jsonapi/data/__init__.py
fastapi_rest_jsonapi/data/data_layer.py
fastapi_rest_jsonapi/data/sqlachemy_data_layer.py
fastapi_rest_jsonapi/request/__init__.py
fastapi_rest_jsonapi/request/field.py
fastapi_rest_jsonapi/request/include.py
fastapi_rest_jsonapi/request/page.py
fastapi_rest_jsonapi/request/request_context.py
fastapi_rest_jsonapi/request/sort.py
fastapi_rest_jsonapi/resource/__init__.py
fastapi_rest_jsonapi/resource/resource.py
fastapi_rest_jsonapi/resource/resource_detail.py
fastapi_rest_jsonapi/resource/resource_list.py
fastapi_rest_jsonapi/resource/utils.py
fastapi_rest_jsonapi/response/__init__.py
fastapi_rest_jsonapi/response/response.py
fastapi_rest_jsonapi/schema/__init__.py
fastapi_rest_jsonapi/schema/fields.py
fastapi_rest_jsonapi/schema/schema.py
FastAPI_REST_JSONAPI-0.8.dist-info/LICENSE
FastAPI_REST_JSONAPI-0.8.dist-info/METADATA
FastAPI_REST_JSONAPI-0.8.dist-info/WHEEL
FastAPI_REST_JSONAPI-0.8.dist-info/top_level.txt
FastAPI_REST_JSONAPI-0.8.dist-info/RECORD
